{
  "version": 2,
  "projects": {
    "add-child-feature": "libs/add-child/feature",
    "admin-console-feature": "libs/admin-console/feature",
    "au-pair-cost-feature": "libs/au-pair-cost/feature",
    "au-pair-dashboard-feature": "libs/au-pair-dashboard/feature",
    "au-pair-profile-feature": "libs/au-pair-profile/feature",
    "au-pair-schedule-feature": "libs/au-pair-schedule/feature",
    "children-dashboard-feature": "libs/children-dashboard/feature",
    "edit-au-pair-profile-feature": "libs/edit-au-pair-profile/feature",
    "edit-child-feature": "libs/edit-child/feature",
    "edit-parent-profile-feature": "libs/edit-parent-profile/feature",
    "explore-feature": "libs/explore/feature",
    "forgot-password-feature": "libs/forgot-password/feature",
    "login-feature": "libs/login/feature",
    "parent-add-activity-feature": "libs/parent-add-activity/feature",
    "parent-dashboard-feature": "libs/parent-dashboard/feature",
    "parent-edit-activity-feature": "libs/parent-edit-activity/feature",
    "parent-notifications-feature": "libs/parent-notifications/feature",
    "parent-profile-feature": "libs/parent-profile/feature",
    "parent-view-activity-feature": "libs/parent-view-activity/feature",
    "register-feature": "libs/register/feature",
    "schedule-feature": "libs/schedule/feature",
    "shared-components-aupair-navbar": "libs/shared/components/aupair-navbar",
    "shared-components-input-field": "libs/shared/components/input-field",
    "shared-components-navbar": "libs/shared/components/navbar",
    "shared-components-admin-navbar": "libs/shared/components/admin-navbar",
    "shared-components-password-field": "libs/shared/components/password-field",
    "shared-components-location-field": "libs/shared/components/location-field",
    "shell-feature": "libs/shell/feature",
    "the-au-pair": "apps/the-au-pair",
    "the-au-pair-e2e": "apps/the-au-pair-e2e",
    "track-au-pair-feature": "libs/track-au-pair/feature"
  }
}
